docs/__init__.py
m3_edm/__init__.py
m3_edm/actions.py
m3_edm/models.py
m3_edm/providers.py
m3_edm/proxies.py
m3_edm/ui.py
m3_edm/functions/__init__.py
m3_edm/functions/change_electronic_document_status/__init__.py
m3_edm/functions/change_electronic_document_status/actions.py
m3_edm/functions/change_electronic_document_status/caches.py
m3_edm/functions/change_electronic_document_status/errors.py
m3_edm/functions/change_electronic_document_status/functions.py
m3_edm/functions/change_electronic_document_status/helpers.py
m3_edm/functions/change_electronic_document_status/managers.py
m3_edm/functions/change_electronic_document_status/runners.py
m3_edm/functions/change_electronic_document_status/strings.py
m3_edm/functions/change_electronic_document_status/validators.py
m3_edm-0.0.14.dist-info/METADATA
m3_edm-0.0.14.dist-info/WHEEL
m3_edm-0.0.14.dist-info/namespace_packages.txt
m3_edm-0.0.14.dist-info/top_level.txt
m3_edm-0.0.14.dist-info/RECORD
