Metadata-Version: 2.1
Name: m3-edm
Version: 0.0.14
Summary: Electronic Document Management
Home-page: http://docs.budg.bars.group/m3_edm/
Download-URL: 
Author: Alexander Danilenko
Author-email: a.danilenko@bars.group
Platform: Any
Classifier: Development Status :: 3 - Alpha
Classifier: License :: OSI Approved :: Apache Software License
Classifier: Programming Language :: Python
Classifier: Programming Language :: Python :: 3
Classifier: Programming Language :: Python :: 3.6
Classifier: Programming Language :: Python :: 3.7
Classifier: Programming Language :: Python :: 3.8
Classifier: Programming Language :: Python :: 3.9
Classifier: Intended Audience :: Developers
Classifier: Environment :: Web Environment
Requires-Dist: function-tools (>=0.1.6)
